LICENSE
MANIFEST.in
README.rst
setup.cfg
setup.py
versioneer.py
tpDcc/__init__.py
tpDcc/dccs/__init__.py
tpDcc/dccs/mobu/__init__.py
tpDcc/dccs/mobu/__logging__.ini
tpDcc/dccs/mobu/__version__.py
tpDcc/dccs/mobu/_version.py
tpDcc/dccs/mobu/dcc.py
tpDcc/dccs/mobu/loader.py
tpDcc/dccs/mobu/core/__init__.py
tpDcc/dccs/mobu/core/gui.py
tpDcc/dccs/mobu/core/helpers.py
tpDcc/dccs/mobu/core/menu.py
tpDcc/dccs/mobu/core/scene.py
tpDcc/dccs/mobu/core/take.py
tpDcc_dccs_mobu.egg-info/PKG-INFO
tpDcc_dccs_mobu.egg-info/SOURCES.txt
tpDcc_dccs_mobu.egg-info/dependency_links.txt
tpDcc_dccs_mobu.egg-info/not-zip-safe
tpDcc_dccs_mobu.egg-info/requires.txt
tpDcc_dccs_mobu.egg-info/top_level.txt