Metadata-Version: 2.1
Name: tpDcc-dccs-mobu
Version: 0.0.1
Summary: MotionBuilder implementation for tpDcc. Utils functions to work with MotionBuilder Python APIs.
Home-page: https://github.com/tpDcc/tpDcc-dccs-mobu
Author: Tomas Poveda
Author-email: tpovedatd@gmail.com
License: MIT
Platform: UNKNOWN
Provides-Extra: dev
Provides-Extra: test
